jtrack/__init__.py
jtrack/main.py
jtrack-1.2.3.dist-info/LICENSE
jtrack-1.2.3.dist-info/METADATA
jtrack-1.2.3.dist-info/WHEEL
jtrack-1.2.3.dist-info/entry_points.txt
jtrack-1.2.3.dist-info/top_level.txt
jtrack-1.2.3.dist-info/RECORD
