Metadata-Version: 2.1
Name: jtrack
Version: 1.2.3
Summary: Fast and effective integration to Jira.
Home-page: https://github.com/rotemreiss/jTrack
Author: Rotem Reiss
Author-email: reiss.r@gmail.com
Classifier: Programming Language :: Python :: 3
Classifier: License :: OSI Approved :: MIT License
Classifier: Operating System :: OS Independent
License-File: LICENSE
Requires-Dist: colorama
Requires-Dist: atlassian-python-api
Requires-Dist: win-unicode-console
